data/VGG16_CLASSES.txt
opengenome/__init__.py
opengenome/welcome.py
opengenome/data/VGG16_CLASSES.txt
opengenome/outputs/__init__.py
opengenome/outputs/cnn.py
opengenome-0.1.4.dist-info/METADATA
opengenome-0.1.4.dist-info/WHEEL
opengenome-0.1.4.dist-info/entry_points.txt
opengenome-0.1.4.dist-info/top_level.txt
opengenome-0.1.4.dist-info/RECORD
