Metadata-Version: 2.2
Name: opengenome
Version: 0.1.4
Home-page: https://opengenome.readthedocs.io/en/latest/
Project-URL: Source, https://github.com/luhouyang/opengenome
Requires-Python: >=3.10
Requires-Dist: torch>=2
Requires-Dist: matplotlib>=3
Requires-Dist: torchinfo>=1.8
Provides-Extra: dev
Requires-Dist: mypy; extra == "dev"
Requires-Dist: pytest; extra == "dev"
Requires-Dist: pytest-cov; extra == "dev"
Requires-Dist: jupyter; extra == "dev"
Requires-Dist: sphinx; extra == "dev"
Requires-Dist: myst-nb; extra == "dev"
Requires-Dist: sphinx-autoapi; extra == "dev"
Requires-Dist: pydata_sphinx_theme; extra == "dev"
Dynamic: description
Dynamic: description-content-type
Dynamic: home-page
Dynamic: project-url
Dynamic: provides-extra
Dynamic: requires-dist
Dynamic: requires-python
